comicapi/__init__.py
comicapi/_url.py
comicapi/comicarchive.py
comicapi/filenamelexer.py
comicapi/filenameparser.py
comicapi/genericmetadata.py
comicapi/issuestring.py
comicapi/merge.py
comicapi/utils.py
comicapi/__pyinstaller/__init__.py
comicapi/__pyinstaller/hook-comicapi.py
comicapi/archivers/__init__.py
comicapi/archivers/archiver.py
comicapi/archivers/folder.py
comicapi/archivers/rar.py
comicapi/archivers/sevenzip.py
comicapi/archivers/zip.py
comicapi/data/__init__.py
comicapi/data/publishers.json
comicapi/tags/__init__.py
comicapi/tags/comet.py
comicapi/tags/comicbookinfo.py
comicapi/tags/comicrack.py
comicapi/tags/tag.py
comictaggerlib/__init__.py
comictaggerlib/__main__.py
comictaggerlib/applicationlogwindow.py
comictaggerlib/autotagmatchwindow.py
comictaggerlib/autotagprogresswindow.py
comictaggerlib/autotagstartwindow.py
comictaggerlib/cbltransformer.py
comictaggerlib/cli.py
comictaggerlib/coverimagewidget.py
comictaggerlib/crediteditorwindow.py
comictaggerlib/ctversion.py
comictaggerlib/defaults.py
comictaggerlib/exportwindow.py
comictaggerlib/filerenamer.py
comictaggerlib/fileselectionlist.py
comictaggerlib/gui.py
comictaggerlib/imagefetcher.py
comictaggerlib/imagehasher.py
comictaggerlib/imagepopup.py
comictaggerlib/issueidentifier.py
comictaggerlib/issueselectionwindow.py
comictaggerlib/log.py
comictaggerlib/logwindow.py
comictaggerlib/main.py
comictaggerlib/matchselectionwindow.py
comictaggerlib/md.py
comictaggerlib/optionalmsgdialog.py
comictaggerlib/pagebrowser.py
comictaggerlib/pagelisteditor.py
comictaggerlib/pageloader.py
comictaggerlib/progresswindow.py
comictaggerlib/quick_tag.py
comictaggerlib/renamewindow.py
comictaggerlib/resulttypes.py
comictaggerlib/seriesselectionwindow.py
comictaggerlib/settingswindow.py
comictaggerlib/taggerwindow.py
comictaggerlib/versionchecker.py
comictaggerlib/__pyinstaller/__init__.py
comictaggerlib/__pyinstaller/hook-comictaggerlib.py
comictaggerlib/__pyinstaller/hook-wordninja.py
comictagger-1.6.0a22.dist-info/LICENSE
comictagger-1.6.0a22.dist-info/METADATA
comictagger-1.6.0a22.dist-info/WHEEL
comictagger-1.6.0a22.dist-info/entry_points.txt
comictagger-1.6.0a22.dist-info/top_level.txt
comictagger-1.6.0a22.dist-info/RECORD
