Metadata-Version: 2.1
Name: comictagger
Version: 1.6.0a22
Summary: A cross-platform GUI/CLI app for writing metadata to comic archives
Home-page: https://github.com/comictagger/comictagger
Author: ComicTagger team
Author-email: comictagger@gmail.com
License: Apache-2.0
Keywords: comictagger,comics,comic,metadata,tagging,tagger
Classifier: Development Status :: 4 - Beta
Classifier: Environment :: Console
Classifier: Environment :: MacOS X
Classifier: Environment :: Win32 (MS Windows)
Classifier: Environment :: X11 Applications :: Qt
Classifier: Intended Audience :: End Users/Desktop
Classifier: License :: OSI Approved :: Apache Software License
Classifier: Natural Language :: English
Classifier: Operating System :: OS Independent
Classifier: Programming Language :: Python :: 3
Classifier: Programming Language :: Python :: 3 :: Only
Classifier: Topic :: Multimedia :: Graphics
Classifier: Topic :: Other/Nonlisted Topic
Classifier: Topic :: Utilities
Requires-Python: >=3.9
License-File: LICENSE
Requires-Dist: appdirs==1.4.4
Requires-Dist: beautifulsoup4>=4.1
Requires-Dist: chardet<6,>=5.1.0
Requires-Dist: comicfn2dict>=0.2.1
Requires-Dist: importlib-metadata>=3.3.0
Requires-Dist: isocodes>=2023.11.26
Requires-Dist: natsort>=8.1.0
Requires-Dist: packaging>=20
Requires-Dist: pathvalidate
Requires-Dist: pillow<10,>=9.1.0
Requires-Dist: pyrate-limiter<3,>=2.6
Requires-Dist: pyyaml
Requires-Dist: rapidfuzz>=2.12.0
Requires-Dist: requests==2.*
Requires-Dist: settngs==0.10.4
Requires-Dist: text2digits
Requires-Dist: typing-extensions>=4.3.0
Requires-Dist: wordninja
Provides-Extra: 7z
Requires-Dist: py7zr; extra == "7z"
Provides-Extra: cbr
Requires-Dist: rarfile>=4.0; extra == "cbr"
Provides-Extra: gui
Requires-Dist: PyQt5; extra == "gui"
Provides-Extra: icu
Requires-Dist: pyicu; (sys_platform == "linux" or sys_platform == "darwin") and extra == "icu"
Provides-Extra: qtw
Requires-Dist: PyQt5; extra == "qtw"
Requires-Dist: PyQtWebEngine; extra == "qtw"
Provides-Extra: all
Requires-Dist: PyQt5; extra == "all"
Requires-Dist: PyQtWebEngine; extra == "all"
Requires-Dist: comicinfoxml==0.4.*; extra == "all"
Requires-Dist: gcd-talker>0.1.0; extra == "all"
Requires-Dist: metron-talker>0.1.5; extra == "all"
Requires-Dist: pillow-avif-plugin>=1.4.1; extra == "all"
Requires-Dist: pillow-jxl-plugin>=1.2.5; extra == "all"
Requires-Dist: py7zr; extra == "all"
Requires-Dist: rarfile>=4.0; extra == "all"
Requires-Dist: pyicu; (sys_platform == "linux" or sys_platform == "darwin") and extra == "all"
Provides-Extra: avif
Requires-Dist: pillow-avif-plugin>=1.4.1; extra == "avif"
Provides-Extra: cix
Requires-Dist: comicinfoxml==0.4.*; extra == "cix"
Provides-Extra: gcd
Requires-Dist: gcd-talker>=0.1.0; extra == "gcd"
Provides-Extra: jxl
Requires-Dist: pillow-jxl-plugin>=1.2.5; extra == "jxl"
Provides-Extra: metron
Requires-Dist: metron-talker>=0.1.3; extra == "metron"
